models/__init__.py
models/product.py
scraper/__init__.py
scraper/amazon.py
scraper/utils/__init__.py
scraper/utils/headers.py
scraper/utils/reg.py
dk_amazon_scraper-0.1.0.dist-info/METADATA
dk_amazon_scraper-0.1.0.dist-info/WHEEL
dk_amazon_scraper-0.1.0.dist-info/top_level.txt
dk_amazon_scraper-0.1.0.dist-info/RECORD
