Metadata-Version: 2.2
Name: dk-amazon_scraper
Version: 0.1.0
Summary: A package for scraping Amazon product details using ASIN
Home-page: https://github.com/dibas9110/amazon_scraper
Author: DK
Author-email: dibas9110@gmail.com
Classifier: Programming Language :: Python :: 3
Classifier: License :: OSI Approved :: MIT License
Classifier: Operating System :: OS Independent
Requires-Python: >=3.10
Requires-Dist: httpx
Requires-Dist: beautifulsoup4
Requires-Dist: pydantic
Dynamic: author
Dynamic: author-email
Dynamic: classifier
Dynamic: description-content-type
Dynamic: home-page
Dynamic: requires-dist
Dynamic: requires-python
Dynamic: summary
